README.md
setup.py
antchain_ebc.egg-info/PKG-INFO
antchain_ebc.egg-info/SOURCES.txt
antchain_ebc.egg-info/dependency_links.txt
antchain_ebc.egg-info/requires.txt
antchain_ebc.egg-info/top_level.txt
antchain_sdk_ebc/__init__.py
antchain_sdk_ebc/client.py
antchain_sdk_ebc/models.py